{"title":"Babes.19.03.05.Eliza.Ibarra.The.Breeders.Part.1.XXX.1080p.MP4...","magnet":"magnet:?xt=urn:btih:125bbebbedcbd373089817707e15ce5163fb34c4&dn=Babes.19.03.05.Eliza.Ibarra.The.Breeders.Part.1.XXX.1080p.MP4...&tr=udp%3A%2F%2Ftracker.leechers-paradise.org%3A6969&tr=udp%3A%2F%2Fzer0day.ch%3A1337&tr=udp%3A%2F%2Fopen.demonii.com%3A1337&tr=udp%3A%2F%2Ftracker.coppersurfer.tk%3A6969&tr=udp%3A%2F%2Fexodus.desync.com%3A6969","uploader":"juggs99","categoryP":"porn","categoryS":"hd___movies","size":"971188493","seeders":"15","leechers":"16","description":"\nBabes.19.03.05.Eliza.Ibarra.The.Breeders.Part.1.XXX.1080p.MP4-KTR \r\n\n\n[Format]:    MPEG-4\n[Duration]:    25 min 28 s\n[Resolution]:  1 920 x 1 080 pixels\n[Display aspect ratio]:    16:9\n[Frame rate mode]:    Constant\n[Frame rate]:    23.976 (24000/1001) FPS\n[Frame rate]:    46.875 FPS (1024 SPF)\n\r\n\n#N1C -&gt; To avoid fakes, ALWAYS check that the torrent was added by NO1CARES\r <a href=\"\nhttps://www.ettv.be/\" rel=\"nofollow\" target=\"_NEW\">\nhttps://www.ettv.be/</a> \r\n <a href=\"\nhttps://www.xxximagetpb.org/image/evrn3M\" rel=\"nofollow\" target=\"_NEW\">\nhttps://www.xxximagetpb.org/image/evrn3M</a>\r <a href=\"\nhttps://www.xxximagetpb.org/image/evrp4A\" rel=\"nofollow\" target=\"_NEW\">\nhttps://www.xxximagetpb.org/image/evrp4A</a>\r <a href=\"\nhttps://www.xxximagetpb.org/image/evrsVc\" rel=\"nofollow\" target=\"_NEW\">\nhttps://www.xxximagetpb.org/image/evrsVc</a>\r <a href=\"\nhttps://www.xxximagetpb.org/image/evr7qZ\" rel=\"nofollow\" target=\"_NEW\">\nhttps://www.xxximagetpb.org/image/evr7qZ</a>","last_updated":"2019-03-05T10:18:56.315Z","parsed":{"xt":"urn:btih:125bbebbedcbd373089817707e15ce5163fb34c4","dn":"Babes.19.03.05.Eliza.Ibarra.The.Breeders.Part.1.XXX.1080p.MP4...","tr":["udp://exodus.desync.com:6969","udp://open.demonii.com:1337","udp://tracker.coppersurfer.tk:6969","udp://tracker.leechers-paradise.org:6969","udp://zer0day.ch:1337"],"infoHash":"125bbebbedcbd373089817707e15ce5163fb34c4","infoHashBuffer":{"type":"Buffer","data":[18,91,190,187,237,203,211,115,8,152,23,112,126,21,206,81,99,251,52,196]},"name":"Babes.19.03.05.Eliza.Ibarra.The.Breeders.Part.1.XXX.1080p.MP4...","announce":["udp://exodus.desync.com:6969","udp://open.demonii.com:1337","udp://tracker.coppersurfer.tk:6969","udp://tracker.leechers-paradise.org:6969","udp://zer0day.ch:1337"],"urlList":[]}}