{"title":"[ImmoralLive] Daphne Klyde, Dean Van Damme (05.03.2019)","magnet":"magnet:?xt=urn:btih:8edfb7d6dacad1b6e374471d7c89019089206d71&dn=%5BImmoralLive%5D+Daphne+Klyde%2C+Dean+Van+Damme+%2805.03.2019%29&tr=udp%3A%2F%2Ftracker.leechers-paradise.org%3A6969&tr=udp%3A%2F%2Fzer0day.ch%3A1337&tr=udp%3A%2F%2Fopen.demonii.com%3A1337&tr=udp%3A%2F%2Ftracker.coppersurfer.tk%3A6969&tr=udp%3A%2F%2Fexodus.desync.com%3A6969","uploader":"KayWily","categoryP":"porn","categoryS":"movie_clips","size":"619338568","seeders":"0","leechers":"0","description":"[ImmoralLive] Daphne Klyde, Dean Van Damme (05.03.2019)\r\n <a href=\"\nhttp://ipicture.su//img-5c7e4aceabeea.html\" rel=\"nofollow\" target=\"_NEW\">\nhttp://ipicture.su//img-5c7e4aceabeea.html</a>","last_updated":"2019-03-05T10:13:06.270Z","parsed":{"xt":"urn:btih:8edfb7d6dacad1b6e374471d7c89019089206d71","dn":"[ImmoralLive] Daphne Klyde, Dean Van Damme (05.03.2019)","tr":["udp://exodus.desync.com:6969","udp://open.demonii.com:1337","udp://tracker.coppersurfer.tk:6969","udp://tracker.leechers-paradise.org:6969","udp://zer0day.ch:1337"],"infoHash":"8edfb7d6dacad1b6e374471d7c89019089206d71","infoHashBuffer":{"type":"Buffer","data":[142,223,183,214,218,202,209,182,227,116,71,29,124,137,1,144,137,32,109,113]},"name":"[ImmoralLive] Daphne Klyde, Dean Van Damme (05.03.2019)","announce":["udp://exodus.desync.com:6969","udp://open.demonii.com:1337","udp://tracker.coppersurfer.tk:6969","udp://tracker.leechers-paradise.org:6969","udp://zer0day.ch:1337"],"urlList":[]}}