{"title":"[RKPrime] Samantha Garmendia - Squirt Roast","magnet":"magnet:?xt=urn:btih:9b1d15cd0474103ec0659e83c8df489fee159f25&dn=%5BRKPrime%5D+Samantha+Garmendia+-+Squirt+Roast&tr=udp%3A%2F%2Ftracker.leechers-paradise.org%3A6969&tr=udp%3A%2F%2Fzer0day.ch%3A1337&tr=udp%3A%2F%2Fopen.demonii.com%3A1337&tr=udp%3A%2F%2Ftracker.coppersurfer.tk%3A6969&tr=udp%3A%2F%2Fexodus.desync.com%3A6969","uploader":"dastink","categoryP":"porn","categoryS":"hd___movies","size":"3176903531","seeders":"33","leechers":"23","description":"[RKPrime] Samantha Garmendia - Squirt Roast (04.03.2019) [1080p]\r\n <a href=\"\nhttp://imgsalem.com/img-5c7e2d4c7cc86.html\" rel=\"nofollow\" target=\"_NEW\">\nhttp://imgsalem.com/img-5c7e2d4c7cc86.html</a> <a href=\"\nhttp://imgsalem.com/img-5c7e2dc66c57a.html\" rel=\"nofollow\" target=\"_NEW\">\nhttp://imgsalem.com/img-5c7e2dc66c57a.html</a>","last_updated":"2019-03-05T10:16:18.253Z","parsed":{"xt":"urn:btih:9b1d15cd0474103ec0659e83c8df489fee159f25","dn":"[RKPrime] Samantha Garmendia - Squirt Roast","tr":["udp://exodus.desync.com:6969","udp://open.demonii.com:1337","udp://tracker.coppersurfer.tk:6969","udp://tracker.leechers-paradise.org:6969","udp://zer0day.ch:1337"],"infoHash":"9b1d15cd0474103ec0659e83c8df489fee159f25","infoHashBuffer":{"type":"Buffer","data":[155,29,21,205,4,116,16,62,192,101,158,131,200,223,72,159,238,21,159,37]},"name":"[RKPrime] Samantha Garmendia - Squirt Roast","announce":["udp://exodus.desync.com:6969","udp://open.demonii.com:1337","udp://tracker.coppersurfer.tk:6969","udp://tracker.leechers-paradise.org:6969","udp://zer0day.ch:1337"],"urlList":[]}}