{"title":"The.Daily.Show.2019.03.04.A.Total.Shutshow.WEB.x264-TBS[ettv]","magnet":"magnet:?xt=urn:btih:9d2d276d65bbe7ff028d7e343bf27c29cf9bc569&dn=The.Daily.Show.2019.03.04.A.Total.Shutshow.WEB.x264-TBS%5Bettv%5D&tr=udp%3A%2F%2Ftracker.leechers-paradise.org%3A6969&tr=udp%3A%2F%2Fzer0day.ch%3A1337&tr=udp%3A%2F%2Fopen.demonii.com%3A1337&tr=udp%3A%2F%2Ftracker.coppersurfer.tk%3A6969&tr=udp%3A%2F%2Fexodus.desync.com%3A6969","uploader":"ettv","categoryP":"video","categoryS":"tv_shows","size":"204535237","seeders":"0","leechers":"0","description":"\nEt TV Shows\r\n <a href=\"\nhttps://www.ettv.be/home/\" rel=\"nofollow\" target=\"_NEW\">\nhttps://www.ettv.be/home/</a>\n\nThe.Daily.Show.2019.03.04.A.Total.Shutshow.WEB.x264-TBS \r\n\n\n[Format]:    Matroska\n[Duration]:    21mn 14s\n[Resolution]:  960 x 540 pixels\n[Display aspect ratio]:    16:9\n[Frame rate mode]:    Constant\n[Frame rate]:    29.970 fps\n\r\n\n#ettv -&gt; To avoid fakes, ALWAYS check that the torrent was added by ettv\r\n\n\r\n\n\nTo keep us going Support us by donating Bitcoin: 1KsLJXUQzuYnuFZpNp4zsvEXaarKa85ADD\r\n\nScreens...\r <a href=\"\nhttps://www.snoopimages.com/image/Fi4H8\" rel=\"nofollow\" target=\"_NEW\">\nhttps://www.snoopimages.com/image/Fi4H8</a>","last_updated":"2019-03-05T11:48:10.721Z","parsed":{"xt":"urn:btih:9d2d276d65bbe7ff028d7e343bf27c29cf9bc569","dn":"The.Daily.Show.2019.03.04.A.Total.Shutshow.WEB.x264-TBS[ettv]","tr":["udp://exodus.desync.com:6969","udp://open.demonii.com:1337","udp://tracker.coppersurfer.tk:6969","udp://tracker.leechers-paradise.org:6969","udp://zer0day.ch:1337"],"infoHash":"9d2d276d65bbe7ff028d7e343bf27c29cf9bc569","infoHashBuffer":{"type":"Buffer","data":[157,45,39,109,101,187,231,255,2,141,126,52,59,242,124,41,207,155,197,105]},"name":"The.Daily.Show.2019.03.04.A.Total.Shutshow.WEB.x264-TBS[ettv]","announce":["udp://exodus.desync.com:6969","udp://open.demonii.com:1337","udp://tracker.coppersurfer.tk:6969","udp://tracker.leechers-paradise.org:6969","udp://zer0day.ch:1337"],"urlList":[]}}