{"title":"Aquaman.2018.IMAX.2160p.WEB-DL.DD+5.1.HDR.HEVC-MOMA","magnet":"magnet:?xt=urn:btih:d780cb7fad12fd163d23b07598808f7524bdc585&dn=Aquaman.2018.IMAX.2160p.WEB-DL.DD%2B5.1.HDR.HEVC-MOMA&tr=udp%3A%2F%2Ftracker.leechers-paradise.org%3A6969&tr=udp%3A%2F%2Fzer0day.ch%3A1337&tr=udp%3A%2F%2Fopen.demonii.com%3A1337&tr=udp%3A%2F%2Ftracker.coppersurfer.tk%3A6969&tr=udp%3A%2F%2Fexodus.desync.com%3A6969","uploader":"MrStark","categoryP":"video","categoryS":"hd___movies","size":"15750758672","seeders":"3","leechers":"67","description":"Aquaman.2018.IMAX.2160p.WEB-DL.DD+5.1.HDR.HEVC-MOMA\r\n\r\nGeneral\r\nContainer......: Matroska\r\nDuration.......: 2 h 23 min\r\nSize...........: 14.2 GiB\r\n\r\nVideo\r\nCodec..........: HEVC Main 10 @ L5.1 @ Main 10 bits\r\nResolution.....: 3840x2160\r\nBit rate.......: 13.6 Mb/s\r\nFrame rate.....: 23.976 (24000/1001) FPS\r\n\r\nAudio\r\nFormat.........: E-AC-3\r\nChannels.......: 15 objects / 6 channels\r\nBit rate.......: 576 kb/s\r\nLanguage.......: English\r\n\r\nSubtitles\r\nLanguage.......: English\r\n\r\nScreenshots :\r\n <a href=\"\nhttps://malzo.com/i/2019/03/05/E0J.png\" rel=\"nofollow\" target=\"_NEW\">\nhttps://malzo.com/i/2019/03/05/E0J.png</a>\r\n <a href=\"\nhttps://malzo.com/i/2019/03/05/E0Q.png\" rel=\"nofollow\" target=\"_NEW\">\nhttps://malzo.com/i/2019/03/05/E0Q.png</a>\r\n <a href=\"\nhttps://malzo.com/i/2019/03/05/E0C.png\" rel=\"nofollow\" target=\"_NEW\">\nhttps://malzo.com/i/2019/03/05/E0C.png</a>","last_updated":"2019-03-05T10:15:04.712Z","parsed":{"xt":"urn:btih:d780cb7fad12fd163d23b07598808f7524bdc585","dn":"Aquaman.2018.IMAX.2160p.WEB-DL.DD 5.1.HDR.HEVC-MOMA","tr":["udp://exodus.desync.com:6969","udp://open.demonii.com:1337","udp://tracker.coppersurfer.tk:6969","udp://tracker.leechers-paradise.org:6969","udp://zer0day.ch:1337"],"infoHash":"d780cb7fad12fd163d23b07598808f7524bdc585","infoHashBuffer":{"type":"Buffer","data":[215,128,203,127,173,18,253,22,61,35,176,117,152,128,143,117,36,189,197,133]},"name":"Aquaman.2018.IMAX.2160p.WEB-DL.DD 5.1.HDR.HEVC-MOMA","announce":["udp://exodus.desync.com:6969","udp://open.demonii.com:1337","udp://tracker.coppersurfer.tk:6969","udp://tracker.leechers-paradise.org:6969","udp://zer0day.ch:1337"],"urlList":[]}}