{"title":"Magnum P I 2018 S01E17 HDTV x264-SVA","magnet":"magnet:?xt=urn:btih:ffc060ee09b01efe1c98798019c44c9914cf52ae&dn=Magnum+P+I+2018+S01E17+HDTV+x264-SVA&tr=udp%3A%2F%2Ftracker.leechers-paradise.org%3A6969&tr=udp%3A%2F%2Fzer0day.ch%3A1337&tr=udp%3A%2F%2Fopen.demonii.com%3A1337&tr=udp%3A%2F%2Ftracker.coppersurfer.tk%3A6969&tr=udp%3A%2F%2Fexodus.desync.com%3A6969","uploader":"TvTeam","categoryP":"video","categoryS":"tv_shows","size":"398191359","seeders":"16","leechers":"4","description":"~~~~~~~~~~~~~~~~~~~~~~~~~~~~~\r <a href=\" https://torrenting.me\" rel=\"nofollow\" target=\"_NEW\"> https://torrenting.me</a>\r\n\r\n~~~~~~~~~~~~~~~~~~~~~~~~~~~~~\r\n\r\n.Magnum.P.I.2018.S01E17.HDTV.x264-SVA.mkv\r\n\r\nScreens\r\n <a href=\"\nhttps://bitpic.me/v/83/mNlh1KkqbUq82Sv\" rel=\"nofollow\" target=\"_NEW\">\nhttps://bitpic.me/v/83/mNlh1KkqbUq82Sv</a> <a href=\"\nhttps://bitpic.me/v/3/m6yDT0zj2x8wYIw\" rel=\"nofollow\" target=\"_NEW\">\nhttps://bitpic.me/v/3/m6yDT0zj2x8wYIw</a> <a href=\"\nhttps://bitpic.me/v/4/Y9s0YfRoVBfhRHK\" rel=\"nofollow\" target=\"_NEW\">\nhttps://bitpic.me/v/4/Y9s0YfRoVBfhRHK</a> <a href=\"\nhttps://bitpic.me/v/80/wGWspO4vgmJtxk2\" rel=\"nofollow\" target=\"_NEW\">\nhttps://bitpic.me/v/80/wGWspO4vgmJtxk2</a> <a href=\"\nhttps://bitpic.me/v/70/RifuZUeMul3ebKM\" rel=\"nofollow\" target=\"_NEW\">\nhttps://bitpic.me/v/70/RifuZUeMul3ebKM</a> <a href=\"\nhttps://bitpic.me/v/73/AMwmg7lHwBCB85p\" rel=\"nofollow\" target=\"_NEW\">\nhttps://bitpic.me/v/73/AMwmg7lHwBCB85p</a>\r\n\r\n Show Title\t\t: Magnum P.I.\r\n Imdb Link\t\t: http://www.imdb.com/title/tt9162324\r\n\r\n Show Plot\t\t: Directed by Kristin Windell.  With Jay Hernandez, Perdita Weeks, Zachary Knighton, Stephen Hill. Magnum poses as a doctor on a dating app in order to find a killer who may be preying on wealthy men.\r\n\r\n Episode\t\t: Season: 1, Episode: 17\r\n Episode Title\t\t: Magnum P.I.\r\n Release Date\t\t: (2018) (TV Series)\r\n Episode Review\t\t: http://www.imdb.com/title/tt9162324\r\n\r\n\r\n\r\nGeneral Information\r\n Duration\t\t: 00:41:43\r\n Release Size\t        : 379 MB\r\n Video Bitrate\t\t: 1 272 Kbps\r\n Frame Rate\t\t: 23.976 Fps\r\n AAC 2ch\t\t: 128 kbps\r\n Video Resolution\t: 720x404  (16:9)","last_updated":"2019-03-05T10:23:12.882Z","parsed":{"xt":"urn:btih:ffc060ee09b01efe1c98798019c44c9914cf52ae","dn":"Magnum P I 2018 S01E17 HDTV x264-SVA","tr":["udp://exodus.desync.com:6969","udp://open.demonii.com:1337","udp://tracker.coppersurfer.tk:6969","udp://tracker.leechers-paradise.org:6969","udp://zer0day.ch:1337"],"infoHash":"ffc060ee09b01efe1c98798019c44c9914cf52ae","infoHashBuffer":{"type":"Buffer","data":[255,192,96,238,9,176,30,254,28,152,121,128,25,196,76,153,20,207,82,174]},"name":"Magnum P I 2018 S01E17 HDTV x264-SVA","announce":["udp://exodus.desync.com:6969","udp://open.demonii.com:1337","udp://tracker.coppersurfer.tk:6969","udp://tracker.leechers-paradise.org:6969","udp://zer0day.ch:1337"],"urlList":[]}}